setup_freeze.py
setup_freeze-0.1.0.dist-info/DESCRIPTION.rst
setup_freeze-0.1.0.dist-info/METADATA
setup_freeze-0.1.0.dist-info/RECORD
setup_freeze-0.1.0.dist-info/WHEEL
setup_freeze-0.1.0.dist-info/entry_points.txt
setup_freeze-0.1.0.dist-info/metadata.json
setup_freeze-0.1.0.dist-info/top_level.txt
