Metadata-Version: 2.0
Name: setup-freeze
Version: 0.1.0
Summary: Freezes the install_requires in your setup.py
Home-page: https://gitlab.com/abre/setup-freeze
Author: Adam Brenecki
Author-email: adam@brenecki.id.au
License: MIT
Keywords: setup.py setuptools development
Platform: UNKNOWN
Classifier: Development Status :: 4 - Beta
Classifier: Intended Audience :: Developers
Classifier: License :: OSI Approved :: MIT License
Classifier: Operating System :: OS Independent
Classifier: Programming Language :: Python
Classifier: Topic :: Software Development
